bilibili_captions/__init__.py
bilibili_captions/cli.py
bilibili_captions/core.py
bilibili_captions/server.py
bilibili_captions-0.1.20260201.1.dist-info/METADATA
bilibili_captions-0.1.20260201.1.dist-info/WHEEL
bilibili_captions-0.1.20260201.1.dist-info/entry_points.txt
bilibili_captions-0.1.20260201.1.dist-info/licenses/LICENSE
bilibili_captions-0.1.20260201.1.dist-info/RECORD
