Metadata-Version: 2.4
Name: bilibili-captions
Version: 0.1.20260201.1
Summary: B站字幕下载工具，支持 API 获取和 Whisper ASR 生成
Project-URL: Homepage, https://github.com/LuShan123888/Bilibili-Captions
Project-URL: Repository, https://github.com/LuShan123888/Bilibili-Captions
Project-URL: Issues, https://github.com/LuShan123888/Bilibili-Captions/issues
Author-email: Cian <LuShan123888@gmail.com>
License: MIT
License-File: LICENSE
Keywords: asr,bilibili,captions,chinese,mcp,subtitle,whisper
Classifier: Development Status :: 4 - Beta
Classifier: Intended Audience :: Developers
Classifier: License :: OSI Approved :: MIT License
Classifier: Programming Language :: Python :: 3
Classifier: Programming Language :: Python :: 3.10
Classifier: Programming Language :: Python :: 3.11
Classifier: Programming Language :: Python :: 3.12
Classifier: Topic :: Multimedia :: Video
Classifier: Topic :: Software Development :: Libraries :: Python Modules
Requires-Python: >=3.10
Requires-Dist: filelock>=3.20.0
Requires-Dist: httpx>=0.28.1
Requires-Dist: mcp>=1.0.0
Requires-Dist: mlx-whisper>=0.4.0
Requires-Dist: opencc-python-reimplemented>=0.1.7
Requires-Dist: requests>=2.32.5
Requires-Dist: tqdm>=4.66.0
Requires-Dist: urllib3>=2.6.0
Provides-Extra: dev
Requires-Dist: pytest>=8.0.0; extra == 'dev'
Requires-Dist: ruff>=0.9.0; extra == 'dev'
